{
  "fetched_at": "2026-07-10T23:54:38.385518+00:00",
  "search_queries": [
    "สรุปสอบ IC",
    "ข้อสอบ IC",
    "ติวสอบ IC",
    "IC Plain สอบ",
    "สอบผ่าน IC"
  ],
  "new_video_queries": [
    "สรุปสอบ IC",
    "ข้อสอบ IC",
    "ติวสอบ IC",
    "IC Plain สอบ",
    "สอบผ่าน IC"
  ],
  "new_videos_days": 365,
  "channels": [
    {
      "channel_name": "AIMC Knowledge",
      "channel_id": "UCTzgulf5uHzUvCvc2xmbPuw",
      "is_own_channel": false,
      "videos": [
        {
          "video_id": "m0nMtE2p2gU",
          "title": "IC Plain : หมวดที่ 1_บทที่ 1 และ บทที่ 2 - อ.ดวงดี",
          "thumbnail_url": "https://i.ytimg.com/vi/m0nMtE2p2gU/maxresdefault.jpg",
          "duration_seconds": 4565,
          "view_count": 95587,
          "like_count": 1490,
          "comment_count": 62,
          "engagement_rate": 1.62,
          "publish_date": "2021-04-01T02:23:52Z"
        },
        {
          "video_id": "xDpvic3xfXI",
          "title": "IC Plain : หมวดที่ 3_ความรู้เกี่ยวกับผลิตภัณฑ์ตลาดทุน : ตราสารทั่วไป Part 1_อ.ดวงดี",
          "thumbnail_url": "https://i.ytimg.com/vi/xDpvic3xfXI/maxresdefault.jpg",
          "duration_seconds": 2332,
          "view_count": 32302,
          "like_count": 367,
          "comment_count": 4,
          "engagement_rate": 1.15,
          "publish_date": "2021-05-11T06:17:08Z"
        },
        {
          "video_id": "3jX4nZp6PAk",
          "title": "IC Plain : หมวดที่ 2_บทที่ 1_อ.ดวงดี",
          "thumbnail_url": "https://i.ytimg.com/vi/3jX4nZp6PAk/maxresdefault.jpg",
          "duration_seconds": 1760,
          "view_count": 31097,
          "like_count": 322,
          "comment_count": 5,
          "engagement_rate": 1.05,
          "publish_date": "2021-04-22T08:52:40Z"
        },
        {
          "video_id": "xYzUSiIfWFU",
          "title": "IC Plain : หมวดที่ 3_ความรู้เกี่ยวกับผลิตภัณฑ์ตลาดทุน : ตราสารทั่วไป Part 2_อ.ดวงดี",
          "thumbnail_url": "https://i.ytimg.com/vi/xYzUSiIfWFU/maxresdefault.jpg",
          "duration_seconds": 2403,
          "view_count": 23763,
          "like_count": 203,
          "comment_count": 3,
          "engagement_rate": 0.87,
          "publish_date": "2021-05-14T01:30:07Z"
        },
        {
          "video_id": "C6_0bCCIq_I",
          "title": "IC Plain : หมวดที่ 3_ความรู้เกี่ยวกับผลิตภัณฑ์ตลาดทุน : ตราสารทั่วไป Part 3_อ.ดวงดี",
          "thumbnail_url": "https://i.ytimg.com/vi/C6_0bCCIq_I/maxresdefault.jpg",
          "duration_seconds": 2360,
          "view_count": 27274,
          "like_count": 314,
          "comment_count": 15,
          "engagement_rate": 1.21,
          "publish_date": "2021-05-16T01:30:00Z"
        },
        {
          "video_id": "KtnNw_wEaB4",
          "title": "IC Plain : หมวดที่ 1_บทที่ 3 - 6 _อ.ดวงดี",
          "thumbnail_url": "https://i.ytimg.com/vi/KtnNw_wEaB4/maxresdefault.jpg",
          "duration_seconds": 2466,
          "view_count": 33981,
          "like_count": 407,
          "comment_count": 8,
          "engagement_rate": 1.22,
          "publish_date": "2021-04-09T02:43:43Z"
        }
      ]
    },
    {
      "channel_name": "Parinya Academy",
      "channel_id": "UCYmXWNzDiU1V81zqWQrxyMw",
      "is_own_channel": false,
      "videos": [
        {
          "video_id": "1P2smTVWtnk",
          "title": "สรุปข้อสอบ IC License | Plain Product หมวดที่ 1 (พร้อมสอบใน 1 ชั่วโมง)",
          "thumbnail_url": "https://i.ytimg.com/vi/1P2smTVWtnk/hqdefault.jpg",
          "duration_seconds": 3485,
          "view_count": 90310,
          "like_count": 2139,
          "comment_count": 53,
          "engagement_rate": 2.43,
          "publish_date": "2022-10-19T04:01:25Z"
        },
        {
          "video_id": "oT0keVyln-g",
          "title": "ตะลุยโจทย์แนวข้อสอบ IC License | EP.1 IC Plain ชุดที่ 1 (แนวข้อสอบจริง)",
          "thumbnail_url": "https://i.ytimg.com/vi/oT0keVyln-g/maxresdefault.jpg",
          "duration_seconds": 985,
          "view_count": 27675,
          "like_count": 564,
          "comment_count": 14,
          "engagement_rate": 2.09,
          "publish_date": "2022-11-28T10:30:11Z"
        },
        {
          "video_id": "zyvAvPEvdBg",
          "title": "สรุปข้อสอบ IC Plain (P1) | หมวด 3 บทที่ 1 ภาพรวมตราสารทุนและหุ้นสามัญ (เข้าใจใน 20 นาที)",
          "thumbnail_url": "https://i.ytimg.com/vi/zyvAvPEvdBg/maxresdefault.jpg",
          "duration_seconds": 1210,
          "view_count": 9205,
          "like_count": 166,
          "comment_count": 0,
          "engagement_rate": 1.8,
          "publish_date": "2022-11-07T09:14:52Z"
        },
        {
          "video_id": "7aoSxxmZAJc",
          "title": "สรุปข้อสอบ IC License | Plain Product หมวดที่ 3 | EP.1 ตราสารทุนและหุ้นสามัญ (ครบจบใน 1 ชั่วโมง)",
          "thumbnail_url": "https://i.ytimg.com/vi/7aoSxxmZAJc/hqdefault.jpg",
          "duration_seconds": 2422,
          "view_count": 18251,
          "like_count": 298,
          "comment_count": 2,
          "engagement_rate": 1.64,
          "publish_date": "2022-11-14T11:38:15Z"
        },
        {
          "video_id": "zExda_lHnEc",
          "title": "สรุปข้อสอบ IC License | Plain Product บทที่ 1 การลงทุนและตลาดการเงิน (สรุปสั้นไม่เกิน 10 นาที)",
          "thumbnail_url": "https://i.ytimg.com/vi/zExda_lHnEc/maxresdefault.jpg",
          "duration_seconds": 453,
          "view_count": 4341,
          "like_count": 93,
          "comment_count": 2,
          "engagement_rate": 2.19,
          "publish_date": "2022-12-12T03:46:58Z"
        }
      ]
    },
    {
      "channel_name": "Alongkorn .S (GogGag)",
      "channel_id": "UCyvCn7dIu5HoWA-IrgMkT1Q",
      "is_own_channel": false,
      "videos": [
        {
          "video_id": "L5V903f585o",
          "title": "IC Plain หมวดที่ 1 Intro บทที่ 1",
          "thumbnail_url": "https://i.ytimg.com/vi/L5V903f585o/maxresdefault.jpg",
          "duration_seconds": 2954,
          "view_count": 114199,
          "like_count": 1231,
          "comment_count": 150,
          "engagement_rate": 1.21,
          "publish_date": "2018-04-25T14:23:54Z"
        }
      ]
    },
    {
      "channel_name": "Gene Panupong",
      "channel_id": "UCUG54YfskEjx0upxhh6qS6g",
      "is_own_channel": false,
      "videos": [
        {
          "video_id": "y5I7HqXqtC8",
          "title": "IC Plain หมวดที่ 1 บทที่ 1 : Smart Wealth อ.ยีน EP.2",
          "thumbnail_url": "https://i.ytimg.com/vi/y5I7HqXqtC8/maxresdefault.jpg",
          "duration_seconds": 1192,
          "view_count": 59683,
          "like_count": 816,
          "comment_count": 43,
          "engagement_rate": 1.44,
          "publish_date": "2020-06-27T02:53:05Z"
        }
      ]
    },
    {
      "channel_name": "ThaiPFA",
      "channel_id": "UCLFDCdJX1DyIIUGapeCIOjg",
      "is_own_channel": false,
      "videos": [
        {
          "video_id": "V7OrWg5EVsY",
          "title": "รู้จักใบอนุญาตผู้แนะนำการลงทุน หรือ IC License และใบอนุญาตผู้วางแผนการลงทุน หรือ IP License |ThaiPFA",
          "thumbnail_url": "https://i.ytimg.com/vi/V7OrWg5EVsY/maxresdefault.jpg",
          "duration_seconds": 412,
          "view_count": 20790,
          "like_count": 379,
          "comment_count": 49,
          "engagement_rate": 2.06,
          "publish_date": "2021-03-20T11:00:18Z"
        },
        {
          "video_id": "TgwBto21Fqw",
          "title": "คนที่จะสอบ IC IP AFPT CFP ต้องเตรียมตัวอย่างไร ถึงจะสอบผ่าน  #การสอบ #CFP #IP #AFPT #IC",
          "thumbnail_url": "https://i.ytimg.com/vi/TgwBto21Fqw/maxresdefault.jpg",
          "duration_seconds": 61,
          "view_count": 6817,
          "like_count": 132,
          "comment_count": 1,
          "engagement_rate": 1.95,
          "publish_date": "2023-10-25T03:00:29Z"
        },
        {
          "video_id": "Cr7ini2GJaM",
          "title": "ใบอนุญาต ผู้แนะนำการลงทุนด้านหลักทรัพย์ IC ผู้วางแผนการลงทุน IP คืออะไรทำงานอย่างไร ได้มาได้อย่างไร",
          "thumbnail_url": "https://i.ytimg.com/vi/Cr7ini2GJaM/maxresdefault.jpg",
          "duration_seconds": 183,
          "view_count": 3729,
          "like_count": 96,
          "comment_count": 11,
          "engagement_rate": 2.87,
          "publish_date": "2023-09-27T00:00:03Z"
        }
      ]
    },
    {
      "channel_name": "การเงินคนโง่",
      "channel_id": "UCkvFq6jKtKEmX3Z2SGQ1mgQ",
      "is_own_channel": false,
      "videos": [
        {
          "video_id": "3oapxVixcvk",
          "title": "ATP Academy | ติวสอบ IC หมวดที่ 1 [บทที่ 1] ปัจจัยแวดล้อมของการลงทุนและตลาดเงิน",
          "thumbnail_url": "https://i.ytimg.com/vi/3oapxVixcvk/maxresdefault.jpg",
          "duration_seconds": 2308,
          "view_count": 24218,
          "like_count": 397,
          "comment_count": 9,
          "engagement_rate": 1.68,
          "publish_date": "2024-04-25T07:54:27Z"
        },
        {
          "video_id": "x2c-ZEaGhWM",
          "title": "ATP Academy | ติวสอบ IC หมวดที่ 1 [บทที่ 3] อัตราผลตอบแทนและความเสี่ยงจากการลงทุนในหลักทรัพย์",
          "thumbnail_url": "https://i.ytimg.com/vi/x2c-ZEaGhWM/maxresdefault.jpg",
          "duration_seconds": 3610,
          "view_count": 6675,
          "like_count": 45,
          "comment_count": 15,
          "engagement_rate": 0.9,
          "publish_date": "2024-04-26T06:28:03Z"
        }
      ]
    },
    {
      "channel_name": "petcharat official",
      "channel_id": "UChbSiqQns1uIpx2YIpTMd0Q",
      "is_own_channel": false,
      "videos": [
        {
          "video_id": "OjJERUuHeVY",
          "title": "ติวสอบ IC หมวดที่ 2 จรรยาบรรณและจริยธรรม",
          "thumbnail_url": "https://i.ytimg.com/vi/OjJERUuHeVY/maxresdefault.jpg",
          "duration_seconds": 6350,
          "view_count": 11034,
          "like_count": 176,
          "comment_count": 5,
          "engagement_rate": 1.64,
          "publish_date": "2023-11-29T10:44:08Z"
        },
        {
          "video_id": "O0dFQGebC84",
          "title": "ติวสอบ IC หมวดที่ 3 บทที่ 8 การซื้อขายตราสารหนี้ในประเทศไทย",
          "thumbnail_url": "https://i.ytimg.com/vi/O0dFQGebC84/maxresdefault.jpg",
          "duration_seconds": 744,
          "view_count": 436,
          "like_count": 3,
          "comment_count": 0,
          "engagement_rate": 0.69,
          "publish_date": "2023-12-03T07:01:05Z"
        },
        {
          "video_id": "_9g8sleep-w",
          "title": "ติวสอบ IC หมวดที่ 1 บทที่ 1 ปัจจัยแวดล้อมของการลงทุนและตลาดเงิน",
          "thumbnail_url": "https://i.ytimg.com/vi/_9g8sleep-w/maxresdefault.jpg",
          "duration_seconds": 2308,
          "view_count": 4431,
          "like_count": 101,
          "comment_count": 6,
          "engagement_rate": 2.41,
          "publish_date": "2023-11-24T10:04:20Z"
        },
        {
          "video_id": "_nQPvS731M0",
          "title": "ติวสอบ IC หมวดที่ 3 บทที่ 2 การประเมินมูลค่าและกลยุทธ์การลงทุนในหุ้นสามัญ",
          "thumbnail_url": "https://i.ytimg.com/vi/_nQPvS731M0/maxresdefault.jpg",
          "duration_seconds": 1488,
          "view_count": 926,
          "like_count": 10,
          "comment_count": 2,
          "engagement_rate": 1.3,
          "publish_date": "2023-12-03T06:45:09Z"
        },
        {
          "video_id": "4XNeJ9xKS9U",
          "title": "ติวสอบ IC หมวดที่ 3 บทที่ 5 ความรู้พื้นฐานเกี่ยวกับตราสารหนี้",
          "thumbnail_url": "https://i.ytimg.com/vi/4XNeJ9xKS9U/maxresdefault.jpg",
          "duration_seconds": 1768,
          "view_count": 677,
          "like_count": 9,
          "comment_count": 1,
          "engagement_rate": 1.48,
          "publish_date": "2023-12-03T06:54:48Z"
        }
      ]
    },
    {
      "channel_name": "ติวโค้งสุดท้ายก่อนสอบ",
      "channel_id": "UCid4JgXfQSi8esMqY0dC8Jg",
      "is_own_channel": false,
      "videos": [
        {
          "video_id": "eRrfMaCjwpA",
          "title": "ติวสอบ IC License สรุปในสรุป Part 1",
          "thumbnail_url": "https://i.ytimg.com/vi/eRrfMaCjwpA/maxresdefault.jpg",
          "duration_seconds": 1022,
          "view_count": 8090,
          "like_count": 186,
          "comment_count": 7,
          "engagement_rate": 2.39,
          "publish_date": "2024-02-08T04:34:31Z"
        },
        {
          "video_id": "HYjpwprsIXM",
          "title": "ติวสอบ IC License สรุปในสรุป Part 3",
          "thumbnail_url": "https://i.ytimg.com/vi/HYjpwprsIXM/maxresdefault.jpg",
          "duration_seconds": 1570,
          "view_count": 4334,
          "like_count": 79,
          "comment_count": 5,
          "engagement_rate": 1.94,
          "publish_date": "2024-02-08T05:39:35Z"
        },
        {
          "video_id": "IFyeEnD2wuM",
          "title": "ติวสอบ IC License สรุปในสรุป Part 2",
          "thumbnail_url": "https://i.ytimg.com/vi/IFyeEnD2wuM/maxresdefault.jpg",
          "duration_seconds": 1076,
          "view_count": 3764,
          "like_count": 69,
          "comment_count": 2,
          "engagement_rate": 1.89,
          "publish_date": "2024-02-08T05:01:36Z"
        }
      ]
    },
    {
      "channel_name": "Rjan Sun CFP",
      "channel_id": "UC_K4nYZ3cm35xa3u2BWFPiw",
      "is_own_channel": false,
      "videos": [
        {
          "video_id": "CwXghlGNGFs",
          "title": "5 สาเหตุที่หลายคนสอบ IC ไม่ผ่านสักที(ติวสอบ IC Plain) + membership",
          "thumbnail_url": "https://i.ytimg.com/vi/CwXghlGNGFs/maxresdefault.jpg",
          "duration_seconds": 394,
          "view_count": 1148,
          "like_count": 19,
          "comment_count": 0,
          "engagement_rate": 1.66,
          "publish_date": "2022-05-18T13:56:06Z"
        },
        {
          "video_id": "5WEO4iHlAx8",
          "title": "6 เทคนิคเตรียมตัวสอบ IC ให้ผ่าน (ติวสอบ IC Plain) + membership",
          "thumbnail_url": "https://i.ytimg.com/vi/5WEO4iHlAx8/maxresdefault.jpg",
          "duration_seconds": 512,
          "view_count": 3782,
          "like_count": 59,
          "comment_count": 7,
          "engagement_rate": 1.75,
          "publish_date": "2022-05-18T14:13:03Z"
        },
        {
          "video_id": "n6LiXJ712uE",
          "title": "เผยคำแนะนำเกี่ยวกับเนื้อหาและหนังสือที่ใช้ในการสอบ IC (ติวสอบ IC Plain)",
          "thumbnail_url": "https://i.ytimg.com/vi/n6LiXJ712uE/maxresdefault.jpg",
          "duration_seconds": 1093,
          "view_count": 1851,
          "like_count": 60,
          "comment_count": 2,
          "engagement_rate": 3.35,
          "publish_date": "2021-05-31T13:01:21Z"
        },
        {
          "video_id": "EZ1VXSJMwoc",
          "title": "เฉลย แบบทดสอบ IC License บทที่ 11 ตราสารหนี้ ติวสอบ IC",
          "thumbnail_url": "https://i.ytimg.com/vi/EZ1VXSJMwoc/maxresdefault.jpg",
          "duration_seconds": 4757,
          "view_count": 6775,
          "like_count": 55,
          "comment_count": 4,
          "engagement_rate": 0.87,
          "publish_date": "2017-12-11T05:27:55Z"
        }
      ]
    },
    {
      "channel_name": "Film Growth Journey ",
      "channel_id": "UCgs5jBu3LmwGFda7kpZ0zvg",
      "is_own_channel": false,
      "videos": [
        {
          "video_id": "SV1hNSEMvkc",
          "title": "สอบ IC ให้ผ่านภายในครั้งเดียว พร้อมแนวข้อสอบ (เวลาน้อย)",
          "thumbnail_url": "https://i.ytimg.com/vi/SV1hNSEMvkc/maxresdefault.jpg",
          "duration_seconds": 355,
          "view_count": 11292,
          "like_count": 453,
          "comment_count": 32,
          "engagement_rate": 4.3,
          "publish_date": "2024-09-24T00:00:15Z"
        }
      ]
    },
    {
      "channel_name": "เป้ แนะแนวการศึกษาและอาชีพ",
      "channel_id": "UCp4g_vp9XZC9Yzx5fv4kkSA",
      "is_own_channel": false,
      "videos": [
        {
          "video_id": "mJcndKOivLY",
          "title": "สอบIC Plainผ่านแต่ไม่อยากขายประกัน #ที่ปรึกษาการลงทุน #การเงิน #การเงินการลงทุน #การเงินส่วนบุคคล",
          "thumbnail_url": "https://i.ytimg.com/vi/mJcndKOivLY/maxresdefault.jpg",
          "duration_seconds": 61,
          "view_count": 5092,
          "like_count": 141,
          "comment_count": 4,
          "engagement_rate": 2.85,
          "publish_date": "2024-12-02T10:51:06Z"
        }
      ]
    },
    {
      "channel_name": "KORN a LOT",
      "channel_id": "UCNb6f1Xkqj3HNWDEUlZS0-w",
      "is_own_channel": false,
      "videos": [
        {
          "video_id": "8vEzg-K03dg",
          "title": "EP. 148 สอบ IC ยังไงให้ครั้งเดียวผ่าน",
          "thumbnail_url": "https://i.ytimg.com/vi/8vEzg-K03dg/maxresdefault.jpg",
          "duration_seconds": 547,
          "view_count": 3957,
          "like_count": 87,
          "comment_count": 14,
          "engagement_rate": 2.55,
          "publish_date": "2025-04-06T10:30:05Z"
        }
      ]
    },
    {
      "channel_name": "ติว IC License โดย Dr Mike",
      "channel_id": "UCgZs-OGL0cOEeV1hl_GqpkQ",
      "is_own_channel": false,
      "videos": [
        {
          "video_id": "boVMPx_FbEQ",
          "title": "ตัวอย่าง คอร์ส IC Plain ออนไลน์ หลักสูตรใหม่ !!",
          "thumbnail_url": "https://i.ytimg.com/vi/boVMPx_FbEQ/maxresdefault.jpg",
          "duration_seconds": 615,
          "view_count": 3315,
          "like_count": 61,
          "comment_count": 7,
          "engagement_rate": 2.05,
          "publish_date": "2020-04-23T12:05:57Z"
        }
      ]
    },
    {
      "channel_name": "Financial Academy",
      "channel_id": "UC4YOsnz8qL-W0NSEtS25Idw",
      "is_own_channel": false,
      "videos": [
        {
          "video_id": "tLRlOaovWvI",
          "title": "เตรียมตัวสอบ IC ต้องทำอย่างไรบ้าง? วันนี้ #financialacademy มีทริคดีๆมาแชร์กันค่า #shorts #การเงิน",
          "thumbnail_url": "https://i.ytimg.com/vi/tLRlOaovWvI/maxresdefault.jpg",
          "duration_seconds": 60,
          "view_count": 3003,
          "like_count": 68,
          "comment_count": 1,
          "engagement_rate": 2.3,
          "publish_date": "2024-11-09T15:50:13Z"
        }
      ]
    },
    {
      "channel_name": "รีวิวให้ที่บ้าน",
      "channel_id": "UCOoFmGqKiB59gqw69-W3quA",
      "is_own_channel": false,
      "videos": [
        {
          "video_id": "U2M9yROR9NY",
          "title": "EP.1 แนะนำการเตรียมสอบ IC Plain (Part 1 / 2 )",
          "thumbnail_url": "https://i.ytimg.com/vi/U2M9yROR9NY/maxresdefault.jpg",
          "duration_seconds": 374,
          "view_count": 2512,
          "like_count": 56,
          "comment_count": 6,
          "engagement_rate": 2.47,
          "publish_date": "2020-12-18T15:35:13Z"
        }
      ]
    },
    {
      "channel_name": "TT DIY Delight",
      "channel_id": "UCoMl8cYY1tvPduLK46AC27w",
      "is_own_channel": false,
      "videos": [
        {
          "video_id": "b-dTcadKVGY",
          "title": "แชร์ประสบการณ์สอบ IC P1, P2, P3 ครั้งเดียวผ่านหมดภายใน 1 เดือน ทำยังไง?",
          "thumbnail_url": "https://i.ytimg.com/vi/b-dTcadKVGY/maxresdefault.jpg",
          "duration_seconds": 1351,
          "view_count": 1983,
          "like_count": 44,
          "comment_count": 2,
          "engagement_rate": 2.32,
          "publish_date": "2024-01-21T14:19:27Z"
        }
      ]
    },
    {
      "channel_name": "NPN Investment",
      "channel_id": "UC2cWuvH0ObhBWMJoa6aU1GA",
      "is_own_channel": false,
      "videos": [
        {
          "video_id": "eZc62aHQD9E",
          "title": "สอบ IC License รอบเดียวผ่าน! เทคนิคจริงที่คนสอบติดใช้กัน",
          "thumbnail_url": "https://i.ytimg.com/vi/eZc62aHQD9E/maxresdefault.jpg",
          "duration_seconds": 920,
          "view_count": 1587,
          "like_count": 50,
          "comment_count": 7,
          "engagement_rate": 3.59,
          "publish_date": "2025-07-19T02:00:06Z"
        }
      ]
    },
    {
      "channel_name": "Muay Saelee",
      "channel_id": "UC-_Byztk5oJAFl3_zwQ9ACw",
      "is_own_channel": false,
      "videos": [
        {
          "video_id": "uJHCjswPDa8",
          "title": "หมูน้อยพาไปสอบ EP.1 | วิธีการสมัครสอบ IC แบบออนไลน์",
          "thumbnail_url": "https://i.ytimg.com/vi/uJHCjswPDa8/maxresdefault.jpg",
          "duration_seconds": 219,
          "view_count": 1091,
          "like_count": 33,
          "comment_count": 12,
          "engagement_rate": 4.12,
          "publish_date": "2021-06-16T10:26:08Z"
        }
      ]
    },
    {
      "channel_name": "Bangkok Investment School",
      "channel_id": "UChaDBx-0HiccQt11j8T4S2g",
      "is_own_channel": false,
      "videos": [
        {
          "video_id": "76QFLxz-Kx0",
          "title": "เรื่องที่ต้องรู้ก่อนสอบ IC License Plain Product (P1: Paper 1)",
          "thumbnail_url": "https://i.ytimg.com/vi/76QFLxz-Kx0/maxresdefault.jpg",
          "duration_seconds": 478,
          "view_count": 291,
          "like_count": 7,
          "comment_count": 1,
          "engagement_rate": 2.75,
          "publish_date": "2022-05-04T10:16:32Z"
        }
      ]
    },
    {
      "channel_name": "ข้อสอบ IC Investment License",
      "channel_id": "UCX_5wcLcU_VylWYEY-reQFQ",
      "is_own_channel": true,
      "videos": [
        {
          "video_id": "nqQggunUhnY",
          "title": "ข้อสอบ IC Plain P1 ทำโจทย์เยอะๆดีกว่าไปเสียค่าสอบหลายรอบ  #ประกัน #ลงทุน #ic",
          "thumbnail_url": "https://i.ytimg.com/vi/nqQggunUhnY/maxresdefault.jpg",
          "duration_seconds": 60,
          "view_count": 201,
          "like_count": 3,
          "comment_count": 2,
          "engagement_rate": 2.49,
          "publish_date": "2026-05-23T14:31:15Z"
        }
      ]
    },
    {
      "channel_name": "อ.บอล สอนIC",
      "channel_id": "UCOaJgBEpW1PahZF4uuqYeog",
      "is_own_channel": false,
      "videos": [
        {
          "video_id": "YLjZEFMAX0s",
          "title": "ติวสอบ IC License หมวด 1 บท 1_2",
          "thumbnail_url": "https://i.ytimg.com/vi/YLjZEFMAX0s/maxresdefault.jpg",
          "duration_seconds": 562,
          "view_count": 24,
          "like_count": 2,
          "comment_count": 0,
          "engagement_rate": 8.33,
          "publish_date": "2024-07-11T11:51:18Z"
        },
        {
          "video_id": "dz4DZdMAVL8",
          "title": "ติวสอบ IC License หมวด 1 บท 1_1",
          "thumbnail_url": "https://i.ytimg.com/vi/dz4DZdMAVL8/maxresdefault.jpg",
          "duration_seconds": 791,
          "view_count": 44,
          "like_count": 3,
          "comment_count": 2,
          "engagement_rate": 11.36,
          "publish_date": "2024-05-12T11:40:21Z"
        }
      ]
    },
    {
      "channel_name": "Smart_Money888",
      "channel_id": "UCLOAG80Bwf3FLJGJSQpem7Q",
      "is_own_channel": false,
      "videos": [
        {
          "video_id": "nwlIuvfbAs0",
          "title": "รีวิว เนื้อหาเตรียมสอบ IC Plain หมวด 1 บทที่ 8",
          "thumbnail_url": "https://i.ytimg.com/vi/nwlIuvfbAs0/maxresdefault.jpg",
          "duration_seconds": 496,
          "view_count": 38,
          "like_count": 1,
          "comment_count": 0,
          "engagement_rate": 2.63,
          "publish_date": "2024-07-18T15:54:23Z"
        }
      ]
    }
  ],
  "new_videos": [
    {
      "video_id": "2jEjREm-lBk",
      "title": "ฝึกทำโจทย์ IC P1 ปี2026 ค่าเบต้า",
      "thumbnail_url": "https://i.ytimg.com/vi/2jEjREm-lBk/maxresdefault.jpg",
      "duration_seconds": 92,
      "view_count": 87,
      "like_count": 2,
      "comment_count": 0,
      "engagement_rate": 2.3,
      "publish_date": "2026-07-07T11:29:08Z",
      "channel_id": "UCX_5wcLcU_VylWYEY-reQFQ",
      "channel_name": "ข้อสอบ IC Investment License",
      "video_url": "https://www.youtube.com/watch?v=2jEjREm-lBk"
    },
    {
      "video_id": "YOuGOBl7Dmk",
      "title": "IC ผ่านได้โดยการทำโจทย์เยอะๆ จะได้ไม่ต้องเสียตังค์สอบหลายรอบ",
      "thumbnail_url": "https://i.ytimg.com/vi/YOuGOBl7Dmk/maxresdefault.jpg",
      "duration_seconds": 68,
      "view_count": 6,
      "like_count": 1,
      "comment_count": 1,
      "engagement_rate": 33.33,
      "publish_date": "2026-07-05T12:29:27Z",
      "channel_id": "UCX_5wcLcU_VylWYEY-reQFQ",
      "channel_name": "ข้อสอบ IC Investment License",
      "video_url": "https://www.youtube.com/watch?v=YOuGOBl7Dmk"
    },
    {
      "video_id": "emPeLENM-48",
      "title": "เฉลยละเอียดแนวข้อสอบ IC ข้อ 1,2",
      "thumbnail_url": "https://i.ytimg.com/vi/emPeLENM-48/maxresdefault.jpg",
      "duration_seconds": 442,
      "view_count": 14,
      "like_count": 1,
      "comment_count": 0,
      "engagement_rate": 7.14,
      "publish_date": "2026-06-29T18:22:51Z",
      "channel_id": "UC9UCdtEHLvk7fNaX05oSvpw",
      "channel_name": "Sukhumalinee",
      "video_url": "https://www.youtube.com/watch?v=emPeLENM-48"
    },
    {
      "video_id": "VB3eHk3S65w",
      "title": "เสียเงินสอบ IC กันไปเท่าไหร่ถึงจะสอบผ่าน ?",
      "thumbnail_url": "https://i.ytimg.com/vi/VB3eHk3S65w/maxresdefault.jpg",
      "duration_seconds": 79,
      "view_count": 419,
      "like_count": 6,
      "comment_count": 1,
      "engagement_rate": 1.67,
      "publish_date": "2026-06-26T15:06:57Z",
      "channel_id": "UCX_5wcLcU_VylWYEY-reQFQ",
      "channel_name": "ข้อสอบ IC Investment License",
      "video_url": "https://www.youtube.com/watch?v=VB3eHk3S65w"
    },
    {
      "video_id": "HeP5xGfxCGk",
      "title": "แกะข้อสอบข้อเขียนและแนวทางการให้คะแนน สอบซ่อม e-CPP ระดับกลาง IC 69",
      "thumbnail_url": "https://i.ytimg.com/vi/HeP5xGfxCGk/maxresdefault.jpg",
      "duration_seconds": 832,
      "view_count": 318,
      "like_count": 15,
      "comment_count": 4,
      "engagement_rate": 5.97,
      "publish_date": "2026-06-26T03:19:27Z",
      "channel_id": "UCEzK_TCYZUtEYApSgOwWoYQ",
      "channel_name": "TAM nopmanie",
      "video_url": "https://www.youtube.com/watch?v=HeP5xGfxCGk"
    },
    {
      "video_id": "FGT3hpzD7mw",
      "title": "พี่หิน Nineplanner 42 เตรียมตัวสอบ IC Plain อย่างไรบ้าง ไปชมกัน",
      "thumbnail_url": "https://i.ytimg.com/vi/FGT3hpzD7mw/maxresdefault.jpg",
      "duration_seconds": 124,
      "view_count": 70,
      "like_count": 1,
      "comment_count": 0,
      "engagement_rate": 1.43,
      "publish_date": "2026-06-24T04:35:28Z",
      "channel_id": "UCfVWloA2NpzGu9x0RMJRAew",
      "channel_name": "Joyuary Phongluangtham",
      "video_url": "https://www.youtube.com/watch?v=FGT3hpzD7mw"
    },
    {
      "video_id": "vVs1sJ-TpXw",
      "title": "AI ช่วยผมสอบ IC ผ่านในสองรอบ #เรียนรู้เอง #selfimprovement",
      "thumbnail_url": "https://i.ytimg.com/vi/vVs1sJ-TpXw/maxresdefault.jpg",
      "duration_seconds": 103,
      "view_count": 1140,
      "like_count": 12,
      "comment_count": 1,
      "engagement_rate": 1.14,
      "publish_date": "2026-06-20T13:23:02Z",
      "channel_id": "UCX_5wcLcU_VylWYEY-reQFQ",
      "channel_name": "ข้อสอบ IC Investment License",
      "video_url": "https://www.youtube.com/watch?v=vVs1sJ-TpXw"
    },
    {
      "video_id": "qUofBBXRAMA",
      "title": "ติวสอบ IC : วิธีหาผลตอบแทนจากการลงทุน",
      "thumbnail_url": "https://i.ytimg.com/vi/qUofBBXRAMA/maxresdefault.jpg",
      "duration_seconds": 243,
      "view_count": 5,
      "like_count": 1,
      "comment_count": 0,
      "engagement_rate": 20.0,
      "publish_date": "2026-06-20T06:00:19Z",
      "channel_id": "UC9UCdtEHLvk7fNaX05oSvpw",
      "channel_name": "Sukhumalinee",
      "video_url": "https://www.youtube.com/watch?v=qUofBBXRAMA"
    },
    {
      "video_id": "snsBCEwH1rU",
      "title": "พี่ช้าง Nineplanner 8 เตรียมตัวสอบ IC Plain ยังไงบ้าง ไปชมกัน",
      "thumbnail_url": "https://i.ytimg.com/vi/snsBCEwH1rU/maxresdefault.jpg",
      "duration_seconds": 126,
      "view_count": 16,
      "like_count": 1,
      "comment_count": 0,
      "engagement_rate": 6.25,
      "publish_date": "2026-06-18T13:39:01Z",
      "channel_id": "UCfVWloA2NpzGu9x0RMJRAew",
      "channel_name": "Joyuary Phongluangtham",
      "video_url": "https://www.youtube.com/watch?v=snsBCEwH1rU"
    },
    {
      "video_id": "yrF-2kL8VHI",
      "title": "เลิกเสียเงินสอบ IC หลายรอบ",
      "thumbnail_url": "https://i.ytimg.com/vi/yrF-2kL8VHI/maxresdefault.jpg",
      "duration_seconds": 80,
      "view_count": 891,
      "like_count": 11,
      "comment_count": 2,
      "engagement_rate": 1.46,
      "publish_date": "2026-06-16T09:34:46Z",
      "channel_id": "UCX_5wcLcU_VylWYEY-reQFQ",
      "channel_name": "ข้อสอบ IC Investment License",
      "video_url": "https://www.youtube.com/watch?v=yrF-2kL8VHI"
    },
    {
      "video_id": "0LGsv--ZSU8",
      "title": "ติวสอบ IC : ข้อสอบให้หาสัดส่วนการลงทุน",
      "thumbnail_url": "https://i.ytimg.com/vi/0LGsv--ZSU8/hqdefault.jpg",
      "duration_seconds": 406,
      "view_count": 18,
      "like_count": 1,
      "comment_count": 0,
      "engagement_rate": 5.56,
      "publish_date": "2026-06-13T15:32:32Z",
      "channel_id": "UC9UCdtEHLvk7fNaX05oSvpw",
      "channel_name": "Sukhumalinee",
      "video_url": "https://www.youtube.com/watch?v=0LGsv--ZSU8"
    },
    {
      "video_id": "QOYmMI0lPh0",
      "title": "IC สามารถสอบผ่านได้ใน 1 เดือน",
      "thumbnail_url": "https://i.ytimg.com/vi/QOYmMI0lPh0/maxresdefault.jpg",
      "duration_seconds": 100,
      "view_count": 1066,
      "like_count": 22,
      "comment_count": 1,
      "engagement_rate": 2.16,
      "publish_date": "2026-06-13T04:55:52Z",
      "channel_id": "UCX_5wcLcU_VylWYEY-reQFQ",
      "channel_name": "ข้อสอบ IC Investment License",
      "video_url": "https://www.youtube.com/watch?v=QOYmMI0lPh0"
    },
    {
      "video_id": "lYeObExtmj8",
      "title": "โจทย์ IC 2026",
      "thumbnail_url": "https://i.ytimg.com/vi/lYeObExtmj8/maxresdefault.jpg",
      "duration_seconds": 111,
      "view_count": 179,
      "like_count": 3,
      "comment_count": 1,
      "engagement_rate": 2.23,
      "publish_date": "2026-06-12T11:54:07Z",
      "channel_id": "UCX_5wcLcU_VylWYEY-reQFQ",
      "channel_name": "ข้อสอบ IC Investment License",
      "video_url": "https://www.youtube.com/watch?v=lYeObExtmj8"
    },
    {
      "video_id": "lg-Zpdz2-WI",
      "title": "สอบ IC ให้ผ่านในรอบเดียว",
      "thumbnail_url": "https://i.ytimg.com/vi/lg-Zpdz2-WI/maxresdefault.jpg",
      "duration_seconds": 83,
      "view_count": 267,
      "like_count": 4,
      "comment_count": 1,
      "engagement_rate": 1.87,
      "publish_date": "2026-05-24T15:04:24Z",
      "channel_id": "UCX_5wcLcU_VylWYEY-reQFQ",
      "channel_name": "ข้อสอบ IC Investment License",
      "video_url": "https://www.youtube.com/watch?v=lg-Zpdz2-WI"
    },
    {
      "video_id": "M8TTSqPo4b0",
      "title": "IC License คืออะไร? แล้ว P1 P2 P3 ต่างกันยังไง? สรุปให้เข้าใจในคลิปเดียว",
      "thumbnail_url": "https://i.ytimg.com/vi/M8TTSqPo4b0/maxresdefault.jpg",
      "duration_seconds": 95,
      "view_count": 1166,
      "like_count": 23,
      "comment_count": 0,
      "engagement_rate": 1.97,
      "publish_date": "2026-04-23T04:31:43Z",
      "channel_id": "UC-QGsm2mc9QW_JthGDf3nLg",
      "channel_name": "สถาบันฝึกอบรม สมาคมบริษัทหลักทรัพย์ไทย (ATI)",
      "video_url": "https://www.youtube.com/watch?v=M8TTSqPo4b0"
    },
    {
      "video_id": "nXxXf3H6WLo",
      "title": "ติวระบบ GFMIS ระบบจัดซื้อจัดจ้าง สำหรับสอบ e-CPP มาตราฐานวิชาชีพพัสดุ หลักสูตร FC ระดับต้น",
      "thumbnail_url": "https://i.ytimg.com/vi/nXxXf3H6WLo/maxresdefault.jpg",
      "duration_seconds": 878,
      "view_count": 313,
      "like_count": 4,
      "comment_count": 0,
      "engagement_rate": 1.28,
      "publish_date": "2026-04-20T04:05:34Z",
      "channel_id": "UCEzK_TCYZUtEYApSgOwWoYQ",
      "channel_name": "TAM nopmanie",
      "video_url": "https://www.youtube.com/watch?v=nXxXf3H6WLo"
    },
    {
      "video_id": "oplG1Ognycs",
      "title": "สรุป 6 เกณฑ์ใหม่ ก.ล.ต. ยกเครื่อง IC/FA อิสระ: เมื่อค่าคอมฯ ไม่ใช่คำตอบสุดท้าย!",
      "thumbnail_url": "https://i.ytimg.com/vi/oplG1Ognycs/hqdefault.jpg",
      "duration_seconds": 914,
      "view_count": 16,
      "like_count": 2,
      "comment_count": 0,
      "engagement_rate": 12.5,
      "publish_date": "2026-02-21T11:01:20Z",
      "channel_id": "UCmYegJYPhdNMTgdIUpvF9Wg",
      "channel_name": "การงง การเงิน ",
      "video_url": "https://www.youtube.com/watch?v=oplG1Ognycs"
    }
  ],
  "insights": [
    {
      "type": "title_pattern",
      "icon": "🏆",
      "tip": "Videos with \"plain\" in the title average 1.7x more views than the niche average",
      "evidence": "Avg views with keyword: 27,890 vs. overall avg: 16,543"
    },
    {
      "type": "timing",
      "icon": "📅",
      "tip": "Videos posted on Wednesday average the highest views in this niche",
      "evidence": "Avg views on Wednesday: 25,822 (based on 9 videos)"
    },
    {
      "type": "engagement",
      "icon": "🔥",
      "tip": "อ.บอล สอนIC drives the most audience interaction — study their format and CTA style",
      "evidence": "Avg engagement rate: 9.84% (likes + comments ÷ views)"
    },
    {
      "type": "content_gap",
      "icon": "🎯",
      "tip": "Top search results use \"ติว\" frequently — your recent videos don't",
      "evidence": "Missing keywords from your titles: ติว, สรุป, แนวข้อสอบ, หมวด"
    },
    {
      "type": "video_length",
      "icon": "⏱",
      "tip": "Top-performing videos average 41m — longer than lower-performing ones (13m)",
      "evidence": "Top 20% avg length: 41m | Bottom 50% avg length: 13m"
    }
  ],
  "audience_questions": [
    {
      "text": "มีหนังสือแนวข้อสอบแนะนำไหมคะ",
      "likes": 0,
      "is_question": true,
      "published_at": "2026-06-28T06:14:04Z",
      "age_days": 12,
      "video_id": "y5I7HqXqtC8",
      "video_title": "IC Plain หมวดที่ 1 บทที่ 1 : Smart Wealth อ.ยีน EP.2",
      "channel_name": "Gene Panupong",
      "video_url": "https://www.youtube.com/watch?v=y5I7HqXqtC8"
    },
    {
      "text": "สอบถามปัจจุบันคับ ตอนนี้ข้อมูลนี้ยังใช่ได้ยุไหมคับ พอดีผมกำลังเตรียมตัวสอบic plain",
      "likes": 0,
      "is_question": true,
      "published_at": "2026-06-16T02:19:07Z",
      "age_days": 24,
      "video_id": "y5I7HqXqtC8",
      "video_title": "IC Plain หมวดที่ 1 บทที่ 1 : Smart Wealth อ.ยีน EP.2",
      "channel_name": "Gene Panupong",
      "video_url": "https://www.youtube.com/watch?v=y5I7HqXqtC8"
    },
    {
      "text": "เนื้อหาสามารถใช้สอบปี 2569 ได้ไหมคะ",
      "likes": 1,
      "is_question": true,
      "published_at": "2026-03-29T16:10:03Z",
      "age_days": 103,
      "video_id": "y5I7HqXqtC8",
      "video_title": "IC Plain หมวดที่ 1 บทที่ 1 : Smart Wealth อ.ยีน EP.2",
      "channel_name": "Gene Panupong",
      "video_url": "https://www.youtube.com/watch?v=y5I7HqXqtC8"
    },
    {
      "text": "ยังใช้ได้อยู่มั้ยคะตอนนี้เค้าเปลี่ยนข้อสอบไปหรือยังคะ",
      "likes": 0,
      "is_question": false,
      "published_at": "2026-07-09T06:06:51Z",
      "age_days": 1,
      "video_id": "1P2smTVWtnk",
      "video_title": "สรุปข้อสอบ IC License | Plain Product หมวดที่ 1 (พร้อมสอบใน 1 ชั่วโมง)",
      "channel_name": "Parinya Academy",
      "video_url": "https://www.youtube.com/watch?v=1P2smTVWtnk"
    },
    {
      "text": "ขอบคุณอาจารย์ดวงดีมากเลยนะคะ สอบผ่านแล้วค่ะ💗🥹 สอนเข้าใจง่าย และ ใช้สอบได้จริงเลยค่ะ🙏🏻",
      "likes": 0,
      "is_question": false,
      "published_at": "2026-07-08T13:17:52Z",
      "age_days": 2,
      "video_id": "m0nMtE2p2gU",
      "video_title": "IC Plain : หมวดที่ 1_บทที่ 1 และ บทที่ 2 - อ.ดวงดี",
      "channel_name": "AIMC Knowledge",
      "video_url": "https://www.youtube.com/watch?v=m0nMtE2p2gU"
    },
    {
      "text": "สุดยอดดด",
      "likes": 1,
      "is_question": false,
      "published_at": "2026-06-09T00:49:40Z",
      "age_days": 31,
      "video_id": "SV1hNSEMvkc",
      "video_title": "สอบ IC ให้ผ่านภายในครั้งเดียว พร้อมแนวข้อสอบ (เวลาน้อย)",
      "channel_name": "Film Growth Journey ",
      "video_url": "https://www.youtube.com/watch?v=SV1hNSEMvkc"
    },
    {
      "text": "อาจารย์สอนดีมากกก เข้าใจมากๆค่ะ",
      "likes": 0,
      "is_question": false,
      "published_at": "2026-05-14T14:29:18Z",
      "age_days": 57,
      "video_id": "3jX4nZp6PAk",
      "video_title": "IC Plain : หมวดที่ 2_บทที่ 1_อ.ดวงดี",
      "channel_name": "AIMC Knowledge",
      "video_url": "https://www.youtube.com/watch?v=3jX4nZp6PAk"
    },
    {
      "text": "ขอบคุณค่ะ สอนดีมากค่ะอาจารย์",
      "likes": 0,
      "is_question": false,
      "published_at": "2026-04-13T07:44:09Z",
      "age_days": 88,
      "video_id": "m0nMtE2p2gU",
      "video_title": "IC Plain : หมวดที่ 1_บทที่ 1 และ บทที่ 2 - อ.ดวงดี",
      "channel_name": "AIMC Knowledge",
      "video_url": "https://www.youtube.com/watch?v=m0nMtE2p2gU"
    },
    {
      "text": "ข้อสอบข้างนอก 300 ข้อนี่ไปหาจากไหนครับ",
      "likes": 0,
      "is_question": false,
      "published_at": "2026-04-07T10:56:49Z",
      "age_days": 94,
      "video_id": "SV1hNSEMvkc",
      "video_title": "สอบ IC ให้ผ่านภายในครั้งเดียว พร้อมแนวข้อสอบ (เวลาน้อย)",
      "channel_name": "Film Growth Journey ",
      "video_url": "https://www.youtube.com/watch?v=SV1hNSEMvkc"
    },
    {
      "text": "ตอนนี้เรียนปี1คณะบริหารธุรกิจสาขาธุรกิจระหว่างประเทศ มีเรียนบัญชีเบื้องต้นพวก งบการเงิน งบกำไรขาดทุน เรียนไปแล้วรู้สึกไม่ค่อยชอบ พี่คิดว่าหนูจะเรียนic ipได้มั้ยคะ มันจะต้องคำนวนแบบบัญชีเยอะมั้ยคะ หรือว่ามองแค่ความเป็นไปได้กับความเสี่ยงของแต่ละธุรกิจ",
      "likes": 1,
      "is_question": false,
      "published_at": "2026-03-26T07:35:47Z",
      "age_days": 106,
      "video_id": "V7OrWg5EVsY",
      "video_title": "รู้จักใบอนุญาตผู้แนะนำการลงทุน หรือ IC License และใบอนุญาตผู้วางแผนการลงทุน หรือ IP License |ThaiPFA",
      "channel_name": "ThaiPFA",
      "video_url": "https://www.youtube.com/watch?v=V7OrWg5EVsY"
    },
    {
      "text": "ติวดีมากค่ะ",
      "likes": 0,
      "is_question": false,
      "published_at": "2026-01-28T05:16:38Z",
      "age_days": 163,
      "video_id": "1P2smTVWtnk",
      "video_title": "สรุปข้อสอบ IC License | Plain Product หมวดที่ 1 (พร้อมสอบใน 1 ชั่วโมง)",
      "channel_name": "Parinya Academy",
      "video_url": "https://www.youtube.com/watch?v=1P2smTVWtnk"
    },
    {
      "text": "ขอบคุณค่า",
      "likes": 0,
      "is_question": false,
      "published_at": "2026-01-24T05:17:14Z",
      "age_days": 167,
      "video_id": "SV1hNSEMvkc",
      "video_title": "สอบ IC ให้ผ่านภายในครั้งเดียว พร้อมแนวข้อสอบ (เวลาน้อย)",
      "channel_name": "Film Growth Journey ",
      "video_url": "https://www.youtube.com/watch?v=SV1hNSEMvkc"
    },
    {
      "text": "ทำ KYC        ไม่ใช่  KTC    นะคะ",
      "likes": 0,
      "is_question": false,
      "published_at": "2026-01-23T06:26:47Z",
      "age_days": 168,
      "video_id": "OjJERUuHeVY",
      "video_title": "ติวสอบ IC หมวดที่ 2 จรรยาบรรณและจริยธรรม",
      "channel_name": "petcharat official",
      "video_url": "https://www.youtube.com/watch?v=OjJERUuHeVY"
    }
  ]
}